nb_ai_context/__init__.py
nb_ai_context/ai_md_generator.py
nb_ai_context/contrib/about.md
nb_ai_context/contrib/gen_github_proj_ai_md.py
nb_ai_context-1.4.dist-info/METADATA
nb_ai_context-1.4.dist-info/WHEEL
nb_ai_context-1.4.dist-info/top_level.txt
nb_ai_context-1.4.dist-info/RECORD
