Metadata-Version: 2.1
Name: nb-ai-context
Version: 1.4
Summary: 非常强力的对任意it项目生成ai上下文单个markdown文档，丢给大模型或者知识库，非常强力，大模型幻觉大幅度减少。尤其是对python项目还有专门的ast语法树解析
Author-email: ydf0509 <ydf0509@xxx.com>
License: MIT
Project-URL: Homepage, https://github.com/ydf0509/nb_ai_context
Project-URL: Repository, https://github.com/ydf0509/nb_ai_context
Project-URL: Issues, https://github.com/ydf0509/nb_ai_context/issues
Keywords: ai,ai context,llm,rag,python,ast,ast metadata,ai context generator,markdown
Classifier: Development Status :: 3 - Alpha
Classifier: Intended Audience :: Developers
Classifier: License :: OSI Approved :: MIT License
Classifier: Programming Language :: Python :: 3
Classifier: Programming Language :: Python :: 3.7
Classifier: Programming Language :: Python :: 3.8
Classifier: Programming Language :: Python :: 3.9
Classifier: Programming Language :: Python :: 3.10
Classifier: Programming Language :: Python :: 3.11
Classifier: Programming Language :: Python :: 3.12
Classifier: Programming Language :: Python :: 3.13
Classifier: Programming Language :: Python :: 3.14
Requires-Python: >=3.7
Requires-Dist: nb-path
Requires-Dist: nb-log
Requires-Dist: typing-extensions >=3.7 ; python_version < "3.8"
Provides-Extra: dev
Requires-Dist: black >=21.0 ; extra == 'dev'
Requires-Dist: flake8 >=3.8 ; extra == 'dev'
Requires-Dist: mypy >=0.812 ; extra == 'dev'
Provides-Extra: test
Requires-Dist: pytest >=6.0 ; extra == 'test'
Requires-Dist: pytest-asyncio >=0.14 ; extra == 'test'
